{"cue_plus":[{"step":0,"cue":1.000,"junction":0.0,"mem":0.2947,"out":0.9666},{"step":1,"cue":0.000,"junction":0.0,"mem":0.3832,"out":0.6147},{"step":2,"cue":0.000,"junction":0.0,"mem":0.6190,"out":0.3302},{"step":3,"cue":0.000,"junction":1.0,"mem":0.7405,"out":0.2958}],"cue_minus":[{"step":0,"cue":-1.000,"junction":0.0,"mem":0.8731,"out":-0.9209},{"step":1,"cue":0.000,"junction":0.0,"mem":1.1147,"out":0.2800},{"step":2,"cue":0.000,"junction":0.0,"mem":1.4294,"out":-0.2012},{"step":3,"cue":0.000,"junction":1.0,"mem":1.6627,"out":-0.1938}]}
